{
  "$schema": "control-panel-design/v1",
  "_meta": {
    "description": "Maps each control panel section to its permitted archetype frames. Services must use these archetypes — no custom shells.",
    "last_updated": "2026-06-21"
  },
  "section_archetypes": {
    "dashboard": {
      "permitted_frames": ["OverviewPageFrame", "MetricsPageFrame"],
      "notes": "Top-level KPI summary and metrics. No queue, no editor."
    },
    "operations": {
      "permitted_frames": ["OperationsRoomFrame", "QueuePageFrame", "DetailPageFrame"],
      "notes": "Live operations room, order queues, delivery detail views."
    },
    "finance": {
      "permitted_frames": ["FinanceReadOnlyFrame", "MetricsPageFrame"],
      "notes": "READ-ONLY. No payment mutation, refund, settlement write. WLT boundary."
    },
    "catalogs": {
      "permitted_frames": ["DataTablePageFrame", "EditorPageFrame", "ReviewPageFrame"],
      "notes": "Product catalog CRUD — table, edit form, review/approve."
    },
    "partners": {
      "permitted_frames": ["QueuePageFrame", "DetailPageFrame", "ReviewPageFrame"],
      "notes": "Partner onboarding queue, partner detail, review workflow."
    },
    "marketing": {
      "permitted_frames": ["OverviewPageFrame", "EditorPageFrame", "MetricsPageFrame"],
      "notes": "Campaign overview, content editor, campaign metrics."
    },
    "support": {
      "permitted_frames": ["QueuePageFrame", "DetailPageFrame"],
      "notes": "Support ticket queue and ticket detail view."
    },
    "platform": {
      "permitted_frames": ["SettingsPageFrame"],
      "notes": "Platform-level configuration and feature flags."
    },
    "administration": {
      "permitted_frames": ["DataTablePageFrame", "SettingsPageFrame"],
      "notes": "User management table and admin settings."
    },
    "hr": {
      "permitted_frames": ["DataTablePageFrame", "QueuePageFrame"],
      "notes": "Staff records table and onboarding/offboarding queues."
    }
  },
  "archetype_source": "shared/app-shell/src/control-panel/archetypes/",
  "archetype_list": [
    "OverviewPageFrame",
    "DataTablePageFrame",
    "QueuePageFrame",
    "OperationsRoomFrame",
    "DetailPageFrame",
    "EditorPageFrame",
    "ReviewPageFrame",
    "MetricsPageFrame",
    "SettingsPageFrame",
    "FinanceReadOnlyFrame"
  ]
}
